opengeode_io/__init__.py
opengeode_io/__init__.pyi
opengeode_io/image_io.py
opengeode_io/image_io.pyi
opengeode_io/mesh_io.py
opengeode_io/mesh_io.pyi
opengeode_io/model_io.py
opengeode_io/model_io.pyi
opengeode_io/py.typed
opengeode_io/lib64/__init__.pyi
opengeode_io/lib64/libOpenGeode-IO_image.so
opengeode_io/lib64/libOpenGeode-IO_mesh.so
opengeode_io/lib64/libOpenGeode-IO_model.so
opengeode_io/lib64/opengeode_io_py_image.cpython-310-x86_64-linux-gnu.so
opengeode_io/lib64/opengeode_io_py_image.pyi
opengeode_io/lib64/opengeode_io_py_mesh.cpython-310-x86_64-linux-gnu.so
opengeode_io/lib64/opengeode_io_py_mesh.pyi
opengeode_io/lib64/opengeode_io_py_model.cpython-310-x86_64-linux-gnu.so
opengeode_io/lib64/opengeode_io_py_model.pyi
opengeode_io-7.4.6.dist-info/METADATA
opengeode_io-7.4.6.dist-info/WHEEL
opengeode_io-7.4.6.dist-info/top_level.txt
opengeode_io-7.4.6.dist-info/RECORD
