Metadata-Version: 2.4
Name: OpenGeode-IO
Version: 7.4.6
Summary: Implementation of input and output formats for OpenGeode
Author-email: Geode-solutions <contact@geode-solutions.com>
License: MIT
Requires-Python: <3.13,>=3.9
Requires-Dist: opengeode-core==15.*,>=15.30.2
